kemampo/__err_type.py
kemampo/__init__.py
kemampo/__kemampo.py
tests/__init__.py
tests/test_crud.py
tests/test_kemampo.py
kemampo-0.0.1.dist-info/LICENSE
kemampo-0.0.1.dist-info/METADATA
kemampo-0.0.1.dist-info/WHEEL
kemampo-0.0.1.dist-info/top_level.txt
kemampo-0.0.1.dist-info/RECORD
