Metadata-Version: 2.1
Name: kemampo
Version: 0.0.1
Summary: A handy, small, library to cut down SQLAlchemy builerplates
Home-page: https://github.com/dolano-tours/kemampo
Author: Erlangga Ibrahim
Author-email: erlanggaibr2@gmail.com
License: UNKNOWN
Platform: UNKNOWN
Classifier: Programming Language :: Python :: 3.7
Classifier: Programming Language :: Python :: 3.8
Classifier: Programming Language :: Python :: 3.9
Classifier: License :: OSI Approved :: GNU General Public License v2 (GPLv2)
Classifier: Operating System :: OS Independent
Requires-Python: >=3.7
